mynd/__init__.py
mynd/config/__init__.py
mynd/config/config_io.py
mynd/database/__init__.py
mynd/database/common.py
mynd/geometry/transformations.py
mynd/geometry/point_cloud/__init__.py
mynd/geometry/point_cloud/point_cloud_io.py
mynd/geometry/point_cloud/point_cloud_processors.py
mynd/geometry/point_cloud/point_cloud_types.py
mynd/geometry/stereo/__init__.py
mynd/geometry/stereo/hitnet.py
mynd/geometry/stereo/pixel_map.py
mynd/geometry/stereo/range_map.py
mynd/geometry/stereo/stereo_geometry.py
mynd/geometry/stereo/stereo_matcher.py
mynd/geometry/stereo/stereo_rectification.py
mynd/image/__init__.py
mynd/image/color_conversion.py
mynd/image/image_io.py
mynd/image/image_processors.py
mynd/image/image_types.py
mynd/records/__init__.py
mynd/records/records.py
mynd/registration/__init__.py
mynd/registration/batch.py
mynd/registration/feature_registrators.py
mynd/registration/full_registrators.py
mynd/registration/icp_registrators.py
mynd/registration/pipeline.py
mynd/registration/pipeline_builder.py
mynd/registration/types.py
mynd/registration/utilities.py
mynd/schemas/__init__.py
mynd/schemas/schemas.py
mynd/tasks/__init__.py
mynd/tasks/camera_assimilation/__init__.py
mynd/tasks/camera_assimilation/alignment.py
mynd/tasks/camera_assimilation/assimilate.py
mynd/tasks/camera_assimilation/transforms.py
mynd/tasks/camera_export/__init__.py
mynd/tasks/camera_export/export.py
mynd/utils/containers.py
mynd/utils/env.py
mynd/utils/filesystem.py
mynd/utils/generators.py
mynd/utils/key_codes.py
mynd/utils/literals.py
mynd/utils/log.py
mynd/utils/time.py
mynd/visualization/gui/__init__.py
mynd/visualization/gui/stereo_visualizer.py
mynd/visualization/plotting/__init__.py
mynd/visualization/plotting/geometry_plotting.py
mynd/visualization/render/__init__.py
mynd/visualization/render/geometry_renderers.py
mynd/visualization/render/image_renderers.py
mynd_lib-0.1.4.dist-info/METADATA
mynd_lib-0.1.4.dist-info/WHEEL
mynd_lib-0.1.4.dist-info/RECORD
