Metadata-Version: 2.4
Name: mynd-lib
Version: 0.1.4
Summary: Mynd core library
Requires-Python: >=3.12
Requires-Dist: arrow>=1.3.0
Requires-Dist: imageio>=2.36.1
Requires-Dist: kornia>=0.7.4
Requires-Dist: loguru>=0.7.3
Requires-Dist: msgspec>=0.19.0
Requires-Dist: numpy>=2.2.1
Requires-Dist: onnxruntime-gpu>=1.21.0
Requires-Dist: onnxruntime>=1.20.1
Requires-Dist: open3d==0.19.0
Requires-Dist: opencv-contrib-python>=4.10.0.84
Requires-Dist: opencv-python>=4.10.0.84
Requires-Dist: plotly>=5.24.1
Requires-Dist: polars[numpy,pandas,pyarrow]>=1.19.0
Requires-Dist: psycopg[binary]>=3.2.4
Requires-Dist: pymap3d>=3.1.0
Requires-Dist: python-dotenv>=1.0.1
Requires-Dist: scipy>=1.15.0
Requires-Dist: sqlalchemy>=2.0.37
Requires-Dist: sqlmodel>=0.0.22
Requires-Dist: tqdm>=4.67.1
